{
  "yangmei": {
    "src": "/assets/preview/sprites/generated/produce-preview-01.png",
    "columns": 4,
    "rows": 4,
    "index": 0,
    "x": 0,
    "y": 0,
    "width": 313,
    "height": 313,
    "sheetWidth": 1252,
    "sheetHeight": 1252,
    "backgroundSize": "400% 400%",
    "backgroundPosition": "0% 0%"
  },
  "lizhi": {
    "src": "/assets/preview/sprites/generated/produce-preview-01.png",
    "columns": 4,
    "rows": 4,
    "index": 1,
    "x": 313,
    "y": 0,
    "width": 313,
    "height": 313,
    "sheetWidth": 1252,
    "sheetHeight": 1252,
    "backgroundSize": "400% 400%",
    "backgroundPosition": "33.3333% 0%"
  },
  "taozi": {
    "src": "/assets/preview/sprites/generated/produce-preview-01.png",
    "columns": 4,
    "rows": 4,
    "index": 2,
    "x": 626,
    "y": 0,
    "width": 313,
    "height": 313,
    "sheetWidth": 1252,
    "sheetHeight": 1252,
    "backgroundSize": "400% 400%",
    "backgroundPosition": "66.6667% 0%"
  },
  "lizi": {
    "src": "/assets/preview/sprites/generated/produce-preview-01.png",
    "columns": 4,
    "rows": 4,
    "index": 3,
    "x": 939,
    "y": 0,
    "width": 313,
    "height": 313,
    "sheetWidth": 1252,
    "sheetHeight": 1252,
    "backgroundSize": "400% 400%",
    "backgroundPosition": "100% 0%"
  },
  "pipa": {
    "src": "/assets/preview/sprites/generated/produce-preview-01.png",
    "columns": 4,
    "rows": 4,
    "index": 4,
    "x": 0,
    "y": 313,
    "width": 313,
    "height": 313,
    "sheetWidth": 1252,
    "sheetHeight": 1252,
    "backgroundSize": "400% 400%",
    "backgroundPosition": "0% 33.3333%"
  },
  "xigua": {
    "src": "/assets/preview/sprites/generated/produce-preview-01.png",
    "columns": 4,
    "rows": 4,
    "index": 5,
    "x": 313,
    "y": 313,
    "width": 313,
    "height": 313,
    "sheetWidth": 1252,
    "sheetHeight": 1252,
    "backgroundSize": "400% 400%",
    "backgroundPosition": "33.3333% 33.3333%"
  },
  "huanggua": {
    "src": "/assets/preview/sprites/generated/produce-preview-01.png",
    "columns": 4,
    "rows": 4,
    "index": 6,
    "x": 626,
    "y": 313,
    "width": 313,
    "height": 313,
    "sheetWidth": 1252,
    "sheetHeight": 1252,
    "backgroundSize": "400% 400%",
    "backgroundPosition": "66.6667% 33.3333%"
  },
  "sigua": {
    "src": "/assets/preview/sprites/generated/produce-preview-01.png",
    "columns": 4,
    "rows": 4,
    "index": 7,
    "x": 939,
    "y": 313,
    "width": 313,
    "height": 313,
    "sheetWidth": 1252,
    "sheetHeight": 1252,
    "backgroundSize": "400% 400%",
    "backgroundPosition": "100% 33.3333%"
  },
  "maodou": {
    "src": "/assets/preview/sprites/generated/produce-preview-01.png",
    "columns": 4,
    "rows": 4,
    "index": 8,
    "x": 0,
    "y": 626,
    "width": 313,
    "height": 313,
    "sheetWidth": 1252,
    "sheetHeight": 1252,
    "backgroundSize": "400% 400%",
    "backgroundPosition": "0% 66.6667%"
  },
  "kongxincai": {
    "src": "/assets/preview/sprites/generated/produce-preview-01.png",
    "columns": 4,
    "rows": 4,
    "index": 9,
    "x": 313,
    "y": 626,
    "width": 313,
    "height": 313,
    "sheetWidth": 1252,
    "sheetHeight": 1252,
    "backgroundSize": "400% 400%",
    "backgroundPosition": "33.3333% 66.6667%"
  },
  "xihongshi": {
    "src": "/assets/preview/sprites/generated/produce-preview-01.png",
    "columns": 4,
    "rows": 4,
    "index": 10,
    "x": 626,
    "y": 626,
    "width": 313,
    "height": 313,
    "sheetWidth": 1252,
    "sheetHeight": 1252,
    "backgroundSize": "400% 400%",
    "backgroundPosition": "66.6667% 66.6667%"
  },
  "qiukui": {
    "src": "/assets/preview/sprites/generated/produce-preview-01.png",
    "columns": 4,
    "rows": 4,
    "index": 11,
    "x": 939,
    "y": 626,
    "width": 313,
    "height": 313,
    "sheetWidth": 1252,
    "sheetHeight": 1252,
    "backgroundSize": "400% 400%",
    "backgroundPosition": "100% 66.6667%"
  },
  "qiezi": {
    "src": "/assets/preview/sprites/generated/produce-preview-01.png",
    "columns": 4,
    "rows": 4,
    "index": 12,
    "x": 0,
    "y": 939,
    "width": 313,
    "height": 313,
    "sheetWidth": 1252,
    "sheetHeight": 1252,
    "backgroundSize": "400% 400%",
    "backgroundPosition": "0% 100%"
  },
  "xiancai": {
    "src": "/assets/preview/sprites/generated/produce-preview-01.png",
    "columns": 4,
    "rows": 4,
    "index": 13,
    "x": 313,
    "y": 939,
    "width": 313,
    "height": 313,
    "sheetWidth": 1252,
    "sheetHeight": 1252,
    "backgroundSize": "400% 400%",
    "backgroundPosition": "33.3333% 100%"
  },
  "caomei": {
    "src": "/assets/preview/sprites/generated/produce-preview-01.png",
    "columns": 4,
    "rows": 4,
    "index": 14,
    "x": 626,
    "y": 939,
    "width": 313,
    "height": 313,
    "sheetWidth": 1252,
    "sheetHeight": 1252,
    "backgroundSize": "400% 400%",
    "backgroundPosition": "66.6667% 100%"
  },
  "putao": {
    "src": "/assets/preview/sprites/generated/produce-preview-01.png",
    "columns": 4,
    "rows": 4,
    "index": 15,
    "x": 939,
    "y": 939,
    "width": 313,
    "height": 313,
    "sheetWidth": 1252,
    "sheetHeight": 1252,
    "backgroundSize": "400% 400%",
    "backgroundPosition": "100% 100%"
  },
  "yingtao": {
    "src": "/assets/preview/sprites/generated/produce-preview-02.png",
    "columns": 4,
    "rows": 4,
    "index": 0,
    "x": 0,
    "y": 0,
    "width": 313,
    "height": 313,
    "sheetWidth": 1252,
    "sheetHeight": 1252,
    "backgroundSize": "400% 400%",
    "backgroundPosition": "0% 0%"
  },
  "mangguo": {
    "src": "/assets/preview/sprites/generated/produce-preview-02.png",
    "columns": 4,
    "rows": 4,
    "index": 1,
    "x": 313,
    "y": 0,
    "width": 313,
    "height": 313,
    "sheetWidth": 1252,
    "sheetHeight": 1252,
    "backgroundSize": "400% 400%",
    "backgroundPosition": "33.3333% 0%"
  },
  "xiangjiao": {
    "src": "/assets/preview/sprites/generated/produce-preview-02.png",
    "columns": 4,
    "rows": 4,
    "index": 2,
    "x": 626,
    "y": 0,
    "width": 313,
    "height": 313,
    "sheetWidth": 1252,
    "sheetHeight": 1252,
    "backgroundSize": "400% 400%",
    "backgroundPosition": "66.6667% 0%"
  },
  "li": {
    "src": "/assets/preview/sprites/generated/produce-preview-02.png",
    "columns": 4,
    "rows": 4,
    "index": 3,
    "x": 939,
    "y": 0,
    "width": 313,
    "height": 313,
    "sheetWidth": 1252,
    "sheetHeight": 1252,
    "backgroundSize": "400% 400%",
    "backgroundPosition": "100% 0%"
  },
  "pingguo": {
    "src": "/assets/preview/sprites/generated/produce-preview-02.png",
    "columns": 4,
    "rows": 4,
    "index": 4,
    "x": 0,
    "y": 313,
    "width": 313,
    "height": 313,
    "sheetWidth": 1252,
    "sheetHeight": 1252,
    "backgroundSize": "400% 400%",
    "backgroundPosition": "0% 33.3333%"
  },
  "chengzi": {
    "src": "/assets/preview/sprites/generated/produce-preview-02.png",
    "columns": 4,
    "rows": 4,
    "index": 5,
    "x": 313,
    "y": 313,
    "width": 313,
    "height": 313,
    "sheetWidth": 1252,
    "sheetHeight": 1252,
    "backgroundSize": "400% 400%",
    "backgroundPosition": "33.3333% 33.3333%"
  },
  "mihoutao": {
    "src": "/assets/preview/sprites/generated/produce-preview-02.png",
    "columns": 4,
    "rows": 4,
    "index": 6,
    "x": 626,
    "y": 313,
    "width": 313,
    "height": 313,
    "sheetWidth": 1252,
    "sheetHeight": 1252,
    "backgroundSize": "400% 400%",
    "backgroundPosition": "66.6667% 33.3333%"
  },
  "shengcai": {
    "src": "/assets/preview/sprites/generated/produce-preview-02.png",
    "columns": 4,
    "rows": 4,
    "index": 7,
    "x": 939,
    "y": 313,
    "width": 313,
    "height": 313,
    "sheetWidth": 1252,
    "sheetHeight": 1252,
    "backgroundSize": "400% 400%",
    "backgroundPosition": "100% 33.3333%"
  },
  "bocai": {
    "src": "/assets/preview/sprites/generated/produce-preview-02.png",
    "columns": 4,
    "rows": 4,
    "index": 8,
    "x": 0,
    "y": 626,
    "width": 313,
    "height": 313,
    "sheetWidth": 1252,
    "sheetHeight": 1252,
    "backgroundSize": "400% 400%",
    "backgroundPosition": "0% 66.6667%"
  },
  "xilanhua": {
    "src": "/assets/preview/sprites/generated/produce-preview-02.png",
    "columns": 4,
    "rows": 4,
    "index": 9,
    "x": 313,
    "y": 626,
    "width": 313,
    "height": 313,
    "sheetWidth": 1252,
    "sheetHeight": 1252,
    "backgroundSize": "400% 400%",
    "backgroundPosition": "33.3333% 66.6667%"
  },
  "baicai": {
    "src": "/assets/preview/sprites/generated/produce-preview-02.png",
    "columns": 4,
    "rows": 4,
    "index": 10,
    "x": 626,
    "y": 626,
    "width": 313,
    "height": 313,
    "sheetWidth": 1252,
    "sheetHeight": 1252,
    "backgroundSize": "400% 400%",
    "backgroundPosition": "66.6667% 66.6667%"
  },
  "huluobo": {
    "src": "/assets/preview/sprites/generated/produce-preview-02.png",
    "columns": 4,
    "rows": 4,
    "index": 11,
    "x": 939,
    "y": 626,
    "width": 313,
    "height": 313,
    "sheetWidth": 1252,
    "sheetHeight": 1252,
    "backgroundSize": "400% 400%",
    "backgroundPosition": "100% 66.6667%"
  },
  "tudou": {
    "src": "/assets/preview/sprites/generated/produce-preview-02.png",
    "columns": 4,
    "rows": 4,
    "index": 12,
    "x": 0,
    "y": 939,
    "width": 313,
    "height": 313,
    "sheetWidth": 1252,
    "sheetHeight": 1252,
    "backgroundSize": "400% 400%",
    "backgroundPosition": "0% 100%"
  },
  "lianou": {
    "src": "/assets/preview/sprites/generated/produce-preview-02.png",
    "columns": 4,
    "rows": 4,
    "index": 13,
    "x": 313,
    "y": 939,
    "width": 313,
    "height": 313,
    "sheetWidth": 1252,
    "sheetHeight": 1252,
    "backgroundSize": "400% 400%",
    "backgroundPosition": "33.3333% 100%"
  },
  "xianggu": {
    "src": "/assets/preview/sprites/generated/produce-preview-02.png",
    "columns": 4,
    "rows": 4,
    "index": 14,
    "x": 626,
    "y": 939,
    "width": 313,
    "height": 313,
    "sheetWidth": 1252,
    "sheetHeight": 1252,
    "backgroundSize": "400% 400%",
    "backgroundPosition": "66.6667% 100%"
  },
  "yumi": {
    "src": "/assets/preview/sprites/generated/produce-preview-02.png",
    "columns": 4,
    "rows": 4,
    "index": 15,
    "x": 939,
    "y": 939,
    "width": 313,
    "height": 313,
    "sheetWidth": 1252,
    "sheetHeight": 1252,
    "backgroundSize": "400% 400%",
    "backgroundPosition": "100% 100%"
  },
  "dasuan": {
    "src": "/assets/preview/sprites/generated/produce-preview-03.png",
    "columns": 4,
    "rows": 4,
    "index": 0,
    "x": 0,
    "y": 0,
    "width": 313,
    "height": 313,
    "sheetWidth": 1252,
    "sheetHeight": 1252,
    "backgroundSize": "400% 400%",
    "backgroundPosition": "0% 0%"
  },
  "xingzi": {
    "src": "/assets/preview/sprites/generated/produce-preview-03.png",
    "columns": 4,
    "rows": 4,
    "index": 1,
    "x": 313,
    "y": 0,
    "width": 313,
    "height": 313,
    "sheetWidth": 1252,
    "sheetHeight": 1252,
    "backgroundSize": "400% 400%",
    "backgroundPosition": "33.3333% 0%"
  },
  "mizi": {
    "src": "/assets/preview/sprites/generated/produce-preview-03.png",
    "columns": 4,
    "rows": 4,
    "index": 2,
    "x": 626,
    "y": 0,
    "width": 313,
    "height": 313,
    "sheetWidth": 1252,
    "sheetHeight": 1252,
    "backgroundSize": "400% 400%",
    "backgroundPosition": "66.6667% 0%"
  },
  "shiliu": {
    "src": "/assets/preview/sprites/generated/produce-preview-03.png",
    "columns": 4,
    "rows": 4,
    "index": 3,
    "x": 939,
    "y": 0,
    "width": 313,
    "height": 313,
    "sheetWidth": 1252,
    "sheetHeight": 1252,
    "backgroundSize": "400% 400%",
    "backgroundPosition": "100% 0%"
  },
  "wuhuaguo": {
    "src": "/assets/preview/sprites/generated/produce-preview-03.png",
    "columns": 4,
    "rows": 4,
    "index": 4,
    "x": 0,
    "y": 313,
    "width": 313,
    "height": 313,
    "sheetWidth": 1252,
    "sheetHeight": 1252,
    "backgroundSize": "400% 400%",
    "backgroundPosition": "0% 33.3333%"
  },
  "hamigua": {
    "src": "/assets/preview/sprites/generated/produce-preview-03.png",
    "columns": 4,
    "rows": 4,
    "index": 5,
    "x": 313,
    "y": 313,
    "width": 313,
    "height": 313,
    "sheetWidth": 1252,
    "sheetHeight": 1252,
    "backgroundSize": "400% 400%",
    "backgroundPosition": "33.3333% 33.3333%"
  },
  "tiangua": {
    "src": "/assets/preview/sprites/generated/produce-preview-03.png",
    "columns": 4,
    "rows": 4,
    "index": 6,
    "x": 626,
    "y": 313,
    "width": 313,
    "height": 313,
    "sheetWidth": 1252,
    "sheetHeight": 1252,
    "backgroundSize": "400% 400%",
    "backgroundPosition": "66.6667% 33.3333%"
  },
  "youzi": {
    "src": "/assets/preview/sprites/generated/produce-preview-03.png",
    "columns": 4,
    "rows": 4,
    "index": 7,
    "x": 939,
    "y": 313,
    "width": 313,
    "height": 313,
    "sheetWidth": 1252,
    "sheetHeight": 1252,
    "backgroundSize": "400% 400%",
    "backgroundPosition": "100% 33.3333%"
  },
  "ganju": {
    "src": "/assets/preview/sprites/generated/produce-preview-03.png",
    "columns": 4,
    "rows": 4,
    "index": 8,
    "x": 0,
    "y": 626,
    "width": 313,
    "height": 313,
    "sheetWidth": 1252,
    "sheetHeight": 1252,
    "backgroundSize": "400% 400%",
    "backgroundPosition": "0% 66.6667%"
  },
  "ningmeng": {
    "src": "/assets/preview/sprites/generated/produce-preview-03.png",
    "columns": 4,
    "rows": 4,
    "index": 9,
    "x": 313,
    "y": 626,
    "width": 313,
    "height": 313,
    "sheetWidth": 1252,
    "sheetHeight": 1252,
    "backgroundSize": "400% 400%",
    "backgroundPosition": "33.3333% 66.6667%"
  },
  "huolongguo": {
    "src": "/assets/preview/sprites/generated/produce-preview-03.png",
    "columns": 4,
    "rows": 4,
    "index": 10,
    "x": 626,
    "y": 626,
    "width": 313,
    "height": 313,
    "sheetWidth": 1252,
    "sheetHeight": 1252,
    "backgroundSize": "400% 400%",
    "backgroundPosition": "66.6667% 66.6667%"
  },
  "boluo": {
    "src": "/assets/preview/sprites/generated/produce-preview-03.png",
    "columns": 4,
    "rows": 4,
    "index": 11,
    "x": 939,
    "y": 626,
    "width": 313,
    "height": 313,
    "sheetWidth": 1252,
    "sheetHeight": 1252,
    "backgroundSize": "400% 400%",
    "backgroundPosition": "100% 66.6667%"
  },
  "mugua": {
    "src": "/assets/preview/sprites/generated/produce-preview-03.png",
    "columns": 4,
    "rows": 4,
    "index": 12,
    "x": 0,
    "y": 939,
    "width": 313,
    "height": 313,
    "sheetWidth": 1252,
    "sheetHeight": 1252,
    "backgroundSize": "400% 400%",
    "backgroundPosition": "0% 100%"
  },
  "shanzha": {
    "src": "/assets/preview/sprites/generated/produce-preview-03.png",
    "columns": 4,
    "rows": 4,
    "index": 13,
    "x": 313,
    "y": 939,
    "width": 313,
    "height": 313,
    "sheetWidth": 1252,
    "sheetHeight": 1252,
    "backgroundSize": "400% 400%",
    "backgroundPosition": "33.3333% 100%"
  },
  "shizi": {
    "src": "/assets/preview/sprites/generated/produce-preview-03.png",
    "columns": 4,
    "rows": 4,
    "index": 14,
    "x": 626,
    "y": 939,
    "width": 313,
    "height": 313,
    "sheetWidth": 1252,
    "sheetHeight": 1252,
    "backgroundSize": "400% 400%",
    "backgroundPosition": "66.6667% 100%"
  },
  "lianwu": {
    "src": "/assets/preview/sprites/generated/produce-preview-03.png",
    "columns": 4,
    "rows": 4,
    "index": 15,
    "x": 939,
    "y": 939,
    "width": 313,
    "height": 313,
    "sheetWidth": 1252,
    "sheetHeight": 1252,
    "backgroundSize": "400% 400%",
    "backgroundPosition": "100% 100%"
  },
  "yangtao": {
    "src": "/assets/preview/sprites/generated/produce-preview-04.png",
    "columns": 4,
    "rows": 4,
    "index": 0,
    "x": 0,
    "y": 0,
    "width": 313,
    "height": 313,
    "sheetWidth": 1252,
    "sheetHeight": 1252,
    "backgroundSize": "400% 400%",
    "backgroundPosition": "0% 0%"
  },
  "sangshen": {
    "src": "/assets/preview/sprites/generated/produce-preview-04.png",
    "columns": 4,
    "rows": 4,
    "index": 1,
    "x": 313,
    "y": 0,
    "width": 313,
    "height": 313,
    "sheetWidth": 1252,
    "sheetHeight": 1252,
    "backgroundSize": "400% 400%",
    "backgroundPosition": "33.3333% 0%"
  },
  "lanmei": {
    "src": "/assets/preview/sprites/generated/produce-preview-04.png",
    "columns": 4,
    "rows": 4,
    "index": 2,
    "x": 626,
    "y": 0,
    "width": 313,
    "height": 313,
    "sheetWidth": 1252,
    "sheetHeight": 1252,
    "backgroundSize": "400% 400%",
    "backgroundPosition": "66.6667% 0%"
  },
  "dongzao": {
    "src": "/assets/preview/sprites/generated/produce-preview-04.png",
    "columns": 4,
    "rows": 4,
    "index": 3,
    "x": 939,
    "y": 0,
    "width": 313,
    "height": 313,
    "sheetWidth": 1252,
    "sheetHeight": 1252,
    "backgroundSize": "400% 400%",
    "backgroundPosition": "100% 0%"
  },
  "liulian": {
    "src": "/assets/preview/sprites/generated/produce-preview-04.png",
    "columns": 4,
    "rows": 4,
    "index": 4,
    "x": 0,
    "y": 313,
    "width": 313,
    "height": 313,
    "sheetWidth": 1252,
    "sheetHeight": 1252,
    "backgroundSize": "400% 400%",
    "backgroundPosition": "0% 33.3333%"
  },
  "kugua": {
    "src": "/assets/preview/sprites/generated/produce-preview-04.png",
    "columns": 4,
    "rows": 4,
    "index": 5,
    "x": 313,
    "y": 313,
    "width": 313,
    "height": 313,
    "sheetWidth": 1252,
    "sheetHeight": 1252,
    "backgroundSize": "400% 400%",
    "backgroundPosition": "33.3333% 33.3333%"
  },
  "donggua": {
    "src": "/assets/preview/sprites/generated/produce-preview-04.png",
    "columns": 4,
    "rows": 4,
    "index": 6,
    "x": 626,
    "y": 313,
    "width": 313,
    "height": 313,
    "sheetWidth": 1252,
    "sheetHeight": 1252,
    "backgroundSize": "400% 400%",
    "backgroundPosition": "66.6667% 33.3333%"
  },
  "nangua": {
    "src": "/assets/preview/sprites/generated/produce-preview-04.png",
    "columns": 4,
    "rows": 4,
    "index": 7,
    "x": 939,
    "y": 313,
    "width": 313,
    "height": 313,
    "sheetWidth": 1252,
    "sheetHeight": 1252,
    "backgroundSize": "400% 400%",
    "backgroundPosition": "100% 33.3333%"
  },
  "foshougua": {
    "src": "/assets/preview/sprites/generated/produce-preview-04.png",
    "columns": 4,
    "rows": 4,
    "index": 8,
    "x": 0,
    "y": 626,
    "width": 313,
    "height": 313,
    "sheetWidth": 1252,
    "sheetHeight": 1252,
    "backgroundSize": "400% 400%",
    "backgroundPosition": "0% 66.6667%"
  },
  "wandou": {
    "src": "/assets/preview/sprites/generated/produce-preview-04.png",
    "columns": 4,
    "rows": 4,
    "index": 9,
    "x": 313,
    "y": 626,
    "width": 313,
    "height": 313,
    "sheetWidth": 1252,
    "sheetHeight": 1252,
    "backgroundSize": "400% 400%",
    "backgroundPosition": "33.3333% 66.6667%"
  },
  "sidou": {
    "src": "/assets/preview/sprites/generated/produce-preview-04.png",
    "columns": 4,
    "rows": 4,
    "index": 10,
    "x": 626,
    "y": 626,
    "width": 313,
    "height": 313,
    "sheetWidth": 1252,
    "sheetHeight": 1252,
    "backgroundSize": "400% 400%",
    "backgroundPosition": "66.6667% 66.6667%"
  },
  "canchai": {
    "src": "/assets/preview/sprites/generated/produce-preview-04.png",
    "columns": 4,
    "rows": 4,
    "index": 11,
    "x": 939,
    "y": 626,
    "width": 313,
    "height": 313,
    "sheetWidth": 1252,
    "sheetHeight": 1252,
    "backgroundSize": "400% 400%",
    "backgroundPosition": "100% 66.6667%"
  },
  "youmaicai": {
    "src": "/assets/preview/sprites/generated/produce-preview-04.png",
    "columns": 4,
    "rows": 4,
    "index": 12,
    "x": 0,
    "y": 939,
    "width": 313,
    "height": 313,
    "sheetWidth": 1252,
    "sheetHeight": 1252,
    "backgroundSize": "400% 400%",
    "backgroundPosition": "0% 100%"
  },
  "xiangcai": {
    "src": "/assets/preview/sprites/generated/produce-preview-04.png",
    "columns": 4,
    "rows": 4,
    "index": 13,
    "x": 313,
    "y": 939,
    "width": 313,
    "height": 313,
    "sheetWidth": 1252,
    "sheetHeight": 1252,
    "backgroundSize": "400% 400%",
    "backgroundPosition": "33.3333% 100%"
  },
  "jiucai": {
    "src": "/assets/preview/sprites/generated/produce-preview-04.png",
    "columns": 4,
    "rows": 4,
    "index": 14,
    "x": 626,
    "y": 939,
    "width": 313,
    "height": 313,
    "sheetWidth": 1252,
    "sheetHeight": 1252,
    "backgroundSize": "400% 400%",
    "backgroundPosition": "66.6667% 100%"
  },
  "cong": {
    "src": "/assets/preview/sprites/generated/produce-preview-04.png",
    "columns": 4,
    "rows": 4,
    "index": 15,
    "x": 939,
    "y": 939,
    "width": 313,
    "height": 313,
    "sheetWidth": 1252,
    "sheetHeight": 1252,
    "backgroundSize": "400% 400%",
    "backgroundPosition": "100% 100%"
  },
  "yangcong": {
    "src": "/assets/preview/sprites/generated/produce-preview-05.png",
    "columns": 4,
    "rows": 4,
    "index": 0,
    "x": 0,
    "y": 0,
    "width": 313,
    "height": 313,
    "sheetWidth": 1252,
    "sheetHeight": 1252,
    "backgroundSize": "400% 400%",
    "backgroundPosition": "0% 0%"
  },
  "baicaitai": {
    "src": "/assets/preview/sprites/generated/produce-preview-05.png",
    "columns": 4,
    "rows": 4,
    "index": 1,
    "x": 313,
    "y": 0,
    "width": 313,
    "height": 313,
    "sheetWidth": 1252,
    "sheetHeight": 1252,
    "backgroundSize": "400% 400%",
    "backgroundPosition": "33.3333% 0%"
  },
  "bailuobo": {
    "src": "/assets/preview/sprites/generated/produce-preview-05.png",
    "columns": 4,
    "rows": 4,
    "index": 2,
    "x": 626,
    "y": 0,
    "width": 313,
    "height": 313,
    "sheetWidth": 1252,
    "sheetHeight": 1252,
    "backgroundSize": "400% 400%",
    "backgroundPosition": "66.6667% 0%"
  },
  "hongshu": {
    "src": "/assets/preview/sprites/generated/produce-preview-05.png",
    "columns": 4,
    "rows": 4,
    "index": 3,
    "x": 939,
    "y": 0,
    "width": 313,
    "height": 313,
    "sheetWidth": 1252,
    "sheetHeight": 1252,
    "backgroundSize": "400% 400%",
    "backgroundPosition": "100% 0%"
  },
  "shanyao": {
    "src": "/assets/preview/sprites/generated/produce-preview-05.png",
    "columns": 4,
    "rows": 4,
    "index": 4,
    "x": 0,
    "y": 313,
    "width": 313,
    "height": 313,
    "sheetWidth": 1252,
    "sheetHeight": 1252,
    "backgroundSize": "400% 400%",
    "backgroundPosition": "0% 33.3333%"
  },
  "sunzi": {
    "src": "/assets/preview/sprites/generated/produce-preview-05.png",
    "columns": 4,
    "rows": 4,
    "index": 5,
    "x": 313,
    "y": 313,
    "width": 313,
    "height": 313,
    "sheetWidth": 1252,
    "sheetHeight": 1252,
    "backgroundSize": "400% 400%",
    "backgroundPosition": "33.3333% 33.3333%"
  },
  "lusun": {
    "src": "/assets/preview/sprites/generated/produce-preview-05.png",
    "columns": 4,
    "rows": 4,
    "index": 6,
    "x": 626,
    "y": 313,
    "width": 313,
    "height": 313,
    "sheetWidth": 1252,
    "sheetHeight": 1252,
    "backgroundSize": "400% 400%",
    "backgroundPosition": "66.6667% 33.3333%"
  },
  "jiaobai": {
    "src": "/assets/preview/sprites/generated/produce-preview-05.png",
    "columns": 4,
    "rows": 4,
    "index": 7,
    "x": 939,
    "y": 313,
    "width": 313,
    "height": 313,
    "sheetWidth": 1252,
    "sheetHeight": 1252,
    "backgroundSize": "400% 400%",
    "backgroundPosition": "100% 33.3333%"
  },
  "oujian": {
    "src": "/assets/preview/sprites/generated/produce-preview-05.png",
    "columns": 4,
    "rows": 4,
    "index": 8,
    "x": 0,
    "y": 626,
    "width": 313,
    "height": 313,
    "sheetWidth": 1252,
    "sheetHeight": 1252,
    "backgroundSize": "400% 400%",
    "backgroundPosition": "0% 66.6667%"
  },
  "qincai": {
    "src": "/assets/preview/sprites/generated/produce-preview-05.png",
    "columns": 4,
    "rows": 4,
    "index": 9,
    "x": 313,
    "y": 626,
    "width": 313,
    "height": 313,
    "sheetWidth": 1252,
    "sheetHeight": 1252,
    "backgroundSize": "400% 400%",
    "backgroundPosition": "33.3333% 66.6667%"
  },
  "huanghuacai": {
    "src": "/assets/preview/sprites/generated/produce-preview-05.png",
    "columns": 4,
    "rows": 4,
    "index": 10,
    "x": 626,
    "y": 626,
    "width": 313,
    "height": 313,
    "sheetWidth": 1252,
    "sheetHeight": 1252,
    "backgroundSize": "400% 400%",
    "backgroundPosition": "66.6667% 66.6667%"
  },
  "cauliflower": {
    "src": "/assets/preview/sprites/generated/produce-preview-05.png",
    "columns": 4,
    "rows": 4,
    "index": 11,
    "x": 939,
    "y": 626,
    "width": 313,
    "height": 313,
    "sheetWidth": 1252,
    "sheetHeight": 1252,
    "backgroundSize": "400% 400%",
    "backgroundPosition": "100% 66.6667%"
  },
  "qingjiao": {
    "src": "/assets/preview/sprites/generated/produce-preview-05.png",
    "columns": 4,
    "rows": 4,
    "index": 12,
    "x": 0,
    "y": 939,
    "width": 313,
    "height": 313,
    "sheetWidth": 1252,
    "sheetHeight": 1252,
    "backgroundSize": "400% 400%",
    "backgroundPosition": "0% 100%"
  },
  "lajiao": {
    "src": "/assets/preview/sprites/generated/produce-preview-05.png",
    "columns": 4,
    "rows": 4,
    "index": 13,
    "x": 313,
    "y": 939,
    "width": 313,
    "height": 313,
    "sheetWidth": 1252,
    "sheetHeight": 1252,
    "backgroundSize": "400% 400%",
    "backgroundPosition": "33.3333% 100%"
  },
  "shengjiang": {
    "src": "/assets/preview/sprites/generated/produce-preview-05.png",
    "columns": 4,
    "rows": 4,
    "index": 14,
    "x": 626,
    "y": 939,
    "width": 313,
    "height": 313,
    "sheetWidth": 1252,
    "sheetHeight": 1252,
    "backgroundSize": "400% 400%",
    "backgroundPosition": "66.6667% 100%"
  },
  "pinggu": {
    "src": "/assets/preview/sprites/generated/produce-preview-05.png",
    "columns": 4,
    "rows": 4,
    "index": 15,
    "x": 939,
    "y": 939,
    "width": 313,
    "height": 313,
    "sheetWidth": 1252,
    "sheetHeight": 1252,
    "backgroundSize": "400% 400%",
    "backgroundPosition": "100% 100%"
  },
  "jinzhengu": {
    "src": "/assets/preview/sprites/generated/produce-preview-06.png",
    "columns": 4,
    "rows": 4,
    "index": 0,
    "x": 0,
    "y": 0,
    "width": 313,
    "height": 313,
    "sheetWidth": 1252,
    "sheetHeight": 1252,
    "backgroundSize": "400% 400%",
    "backgroundPosition": "0% 0%"
  },
  "haixiangu": {
    "src": "/assets/preview/sprites/generated/produce-preview-06.png",
    "columns": 4,
    "rows": 4,
    "index": 1,
    "x": 313,
    "y": 0,
    "width": 313,
    "height": 313,
    "sheetWidth": 1252,
    "sheetHeight": 1252,
    "backgroundSize": "400% 400%",
    "backgroundPosition": "33.3333% 0%"
  },
  "longyan": {
    "src": "/assets/preview/sprites/generated/produce-preview-06.png",
    "columns": 4,
    "rows": 4,
    "index": 2,
    "x": 626,
    "y": 0,
    "width": 313,
    "height": 313,
    "sheetWidth": 1252,
    "sheetHeight": 1252,
    "backgroundSize": "400% 400%",
    "backgroundPosition": "66.6667% 0%"
  },
  "huangpi": {
    "src": "/assets/preview/sprites/generated/produce-preview-06.png",
    "columns": 4,
    "rows": 4,
    "index": 3,
    "x": 939,
    "y": 0,
    "width": 313,
    "height": 313,
    "sheetWidth": 1252,
    "sheetHeight": 1252,
    "backgroundSize": "400% 400%",
    "backgroundPosition": "100% 0%"
  },
  "fanliuzhi": {
    "src": "/assets/preview/sprites/generated/produce-preview-06.png",
    "columns": 4,
    "rows": 4,
    "index": 4,
    "x": 0,
    "y": 313,
    "width": 313,
    "height": 313,
    "sheetWidth": 1252,
    "sheetHeight": 1252,
    "backgroundSize": "400% 400%",
    "backgroundPosition": "0% 33.3333%"
  },
  "baixiangguo": {
    "src": "/assets/preview/sprites/generated/produce-preview-06.png",
    "columns": 4,
    "rows": 4,
    "index": 5,
    "x": 313,
    "y": 313,
    "width": 313,
    "height": 313,
    "sheetWidth": 1252,
    "sheetHeight": 1252,
    "backgroundSize": "400% 400%",
    "backgroundPosition": "33.3333% 33.3333%"
  },
  "hongmaodan": {
    "src": "/assets/preview/sprites/generated/produce-preview-06.png",
    "columns": 4,
    "rows": 4,
    "index": 6,
    "x": 626,
    "y": 313,
    "width": 313,
    "height": 313,
    "sheetWidth": 1252,
    "sheetHeight": 1252,
    "backgroundSize": "400% 400%",
    "backgroundPosition": "66.6667% 33.3333%"
  },
  "shijia": {
    "src": "/assets/preview/sprites/generated/produce-preview-06.png",
    "columns": 4,
    "rows": 4,
    "index": 7,
    "x": 939,
    "y": 313,
    "width": 313,
    "height": 313,
    "sheetWidth": 1252,
    "sheetHeight": 1252,
    "backgroundSize": "400% 400%",
    "backgroundPosition": "100% 33.3333%"
  },
  "niuyouguo": {
    "src": "/assets/preview/sprites/generated/produce-preview-06.png",
    "columns": 4,
    "rows": 4,
    "index": 8,
    "x": 0,
    "y": 626,
    "width": 313,
    "height": 313,
    "sheetWidth": 1252,
    "sheetHeight": 1252,
    "backgroundSize": "400% 400%",
    "backgroundPosition": "0% 66.6667%"
  },
  "yezi": {
    "src": "/assets/preview/sprites/generated/produce-preview-06.png",
    "columns": 4,
    "rows": 4,
    "index": 9,
    "x": 313,
    "y": 626,
    "width": 313,
    "height": 313,
    "sheetWidth": 1252,
    "sheetHeight": 1252,
    "backgroundSize": "400% 400%",
    "backgroundPosition": "33.3333% 66.6667%"
  },
  "boluomi": {
    "src": "/assets/preview/sprites/generated/produce-preview-06.png",
    "columns": 4,
    "rows": 4,
    "index": 10,
    "x": 626,
    "y": 626,
    "width": 313,
    "height": 313,
    "sheetWidth": 1252,
    "sheetHeight": 1252,
    "backgroundSize": "400% 400%",
    "backgroundPosition": "66.6667% 66.6667%"
  },
  "shanzhu": {
    "src": "/assets/preview/sprites/generated/produce-preview-06.png",
    "columns": 4,
    "rows": 4,
    "index": 11,
    "x": 939,
    "y": 626,
    "width": 313,
    "height": 313,
    "sheetWidth": 1252,
    "sheetHeight": 1252,
    "backgroundSize": "400% 400%",
    "backgroundPosition": "100% 66.6667%"
  },
  "renshenguo": {
    "src": "/assets/preview/sprites/generated/produce-preview-06.png",
    "columns": 4,
    "rows": 4,
    "index": 12,
    "x": 0,
    "y": 939,
    "width": 313,
    "height": 313,
    "sheetWidth": 1252,
    "sheetHeight": 1252,
    "backgroundSize": "400% 400%",
    "backgroundPosition": "0% 100%"
  },
  "shepiguo": {
    "src": "/assets/preview/sprites/generated/produce-preview-06.png",
    "columns": 4,
    "rows": 4,
    "index": 13,
    "x": 313,
    "y": 939,
    "width": 313,
    "height": 313,
    "sheetWidth": 1252,
    "sheetHeight": 1252,
    "backgroundSize": "400% 400%",
    "backgroundPosition": "33.3333% 100%"
  },
  "ganlan": {
    "src": "/assets/preview/sprites/generated/produce-preview-06.png",
    "columns": 4,
    "rows": 4,
    "index": 14,
    "x": 626,
    "y": 939,
    "width": 313,
    "height": 313,
    "sheetWidth": 1252,
    "sheetHeight": 1252,
    "backgroundSize": "400% 400%",
    "backgroundPosition": "66.6667% 100%"
  },
  "qingmei": {
    "src": "/assets/preview/sprites/generated/produce-preview-06.png",
    "columns": 4,
    "rows": 4,
    "index": 15,
    "x": 939,
    "y": 939,
    "width": 313,
    "height": 313,
    "sheetWidth": 1252,
    "sheetHeight": 1252,
    "backgroundSize": "400% 400%",
    "backgroundPosition": "100% 100%"
  },
  "nai": {
    "src": "/assets/preview/sprites/generated/produce-preview-07.png",
    "columns": 4,
    "rows": 4,
    "index": 0,
    "x": 0,
    "y": 0,
    "width": 313,
    "height": 313,
    "sheetWidth": 1252,
    "sheetHeight": 1252,
    "backgroundSize": "400% 400%",
    "backgroundPosition": "0% 0%"
  },
  "ximei": {
    "src": "/assets/preview/sprites/generated/produce-preview-07.png",
    "columns": 4,
    "rows": 4,
    "index": 1,
    "x": 313,
    "y": 0,
    "width": 313,
    "height": 313,
    "sheetWidth": 1252,
    "sheetHeight": 1252,
    "backgroundSize": "400% 400%",
    "backgroundPosition": "33.3333% 0%"
  },
  "heibulin": {
    "src": "/assets/preview/sprites/generated/produce-preview-07.png",
    "columns": 4,
    "rows": 4,
    "index": 2,
    "x": 626,
    "y": 0,
    "width": 313,
    "height": 313,
    "sheetWidth": 1252,
    "sheetHeight": 1252,
    "backgroundSize": "400% 400%",
    "backgroundPosition": "66.6667% 0%"
  },
  "youtao": {
    "src": "/assets/preview/sprites/generated/produce-preview-07.png",
    "columns": 4,
    "rows": 4,
    "index": 3,
    "x": 939,
    "y": 0,
    "width": 313,
    "height": 313,
    "sheetWidth": 1252,
    "sheetHeight": 1252,
    "backgroundSize": "400% 400%",
    "backgroundPosition": "100% 0%"
  },
  "hongsu": {
    "src": "/assets/preview/sprites/generated/produce-preview-07.png",
    "columns": 4,
    "rows": 4,
    "index": 4,
    "x": 0,
    "y": 313,
    "width": 313,
    "height": 313,
    "sheetWidth": 1252,
    "sheetHeight": 1252,
    "backgroundSize": "400% 400%",
    "backgroundPosition": "0% 33.3333%"
  },
  "haitangguo": {
    "src": "/assets/preview/sprites/generated/produce-preview-07.png",
    "columns": 4,
    "rows": 4,
    "index": 5,
    "x": 313,
    "y": 313,
    "width": 313,
    "height": 313,
    "sheetWidth": 1252,
    "sheetHeight": 1252,
    "backgroundSize": "400% 400%",
    "backgroundPosition": "33.3333% 33.3333%"
  },
  "shaguo": {
    "src": "/assets/preview/sprites/generated/produce-preview-07.png",
    "columns": 4,
    "rows": 4,
    "index": 6,
    "x": 626,
    "y": 313,
    "width": 313,
    "height": 313,
    "sheetWidth": 1252,
    "sheetHeight": 1252,
    "backgroundSize": "400% 400%",
    "backgroundPosition": "66.6667% 33.3333%"
  },
  "huaishanli": {
    "src": "/assets/preview/sprites/generated/produce-preview-07.png",
    "columns": 4,
    "rows": 4,
    "index": 7,
    "x": 939,
    "y": 313,
    "width": 313,
    "height": 313,
    "sheetWidth": 1252,
    "sheetHeight": 1252,
    "backgroundSize": "400% 400%",
    "backgroundPosition": "100% 33.3333%"
  },
  "youganzi": {
    "src": "/assets/preview/sprites/generated/produce-preview-07.png",
    "columns": 4,
    "rows": 4,
    "index": 8,
    "x": 0,
    "y": 626,
    "width": 313,
    "height": 313,
    "sheetWidth": 1252,
    "sheetHeight": 1252,
    "backgroundSize": "400% 400%",
    "backgroundPosition": "0% 66.6667%"
  },
  "cili": {
    "src": "/assets/preview/sprites/generated/produce-preview-07.png",
    "columns": 4,
    "rows": 4,
    "index": 9,
    "x": 313,
    "y": 626,
    "width": 313,
    "height": 313,
    "sheetWidth": 1252,
    "sheetHeight": 1252,
    "backgroundSize": "400% 400%",
    "backgroundPosition": "33.3333% 66.6667%"
  },
  "shaji": {
    "src": "/assets/preview/sprites/generated/produce-preview-07.png",
    "columns": 4,
    "rows": 4,
    "index": 10,
    "x": 626,
    "y": 626,
    "width": 313,
    "height": 313,
    "sheetWidth": 1252,
    "sheetHeight": 1252,
    "backgroundSize": "400% 400%",
    "backgroundPosition": "66.6667% 66.6667%"
  },
  "gu-niangguo": {
    "src": "/assets/preview/sprites/generated/produce-preview-07.png",
    "columns": 4,
    "rows": 4,
    "index": 11,
    "x": 939,
    "y": 626,
    "width": 313,
    "height": 313,
    "sheetWidth": 1252,
    "sheetHeight": 1252,
    "backgroundSize": "400% 400%",
    "backgroundPosition": "100% 66.6667%"
  },
  "fupenzi": {
    "src": "/assets/preview/sprites/generated/produce-preview-07.png",
    "columns": 4,
    "rows": 4,
    "index": 12,
    "x": 0,
    "y": 939,
    "width": 313,
    "height": 313,
    "sheetWidth": 1252,
    "sheetHeight": 1252,
    "backgroundSize": "400% 400%",
    "backgroundPosition": "0% 100%"
  },
  "heimei": {
    "src": "/assets/preview/sprites/generated/produce-preview-07.png",
    "columns": 4,
    "rows": 4,
    "index": 13,
    "x": 313,
    "y": 939,
    "width": 313,
    "height": 313,
    "sheetWidth": 1252,
    "sheetHeight": 1252,
    "backgroundSize": "400% 400%",
    "backgroundPosition": "33.3333% 100%"
  },
  "man-yuemei": {
    "src": "/assets/preview/sprites/generated/produce-preview-07.png",
    "columns": 4,
    "rows": 4,
    "index": 14,
    "x": 626,
    "y": 939,
    "width": 313,
    "height": 313,
    "sheetWidth": 1252,
    "sheetHeight": 1252,
    "backgroundSize": "400% 400%",
    "backgroundPosition": "66.6667% 100%"
  },
  "heicujili": {
    "src": "/assets/preview/sprites/generated/produce-preview-07.png",
    "columns": 4,
    "rows": 4,
    "index": 15,
    "x": 939,
    "y": 939,
    "width": 313,
    "height": 313,
    "sheetWidth": 1252,
    "sheetHeight": 1252,
    "backgroundSize": "400% 400%",
    "backgroundPosition": "100% 100%"
  },
  "luohanguo": {
    "src": "/assets/preview/sprites/generated/produce-preview-08.png",
    "columns": 4,
    "rows": 4,
    "index": 0,
    "x": 0,
    "y": 0,
    "width": 313,
    "height": 313,
    "sheetWidth": 1252,
    "sheetHeight": 1252,
    "backgroundSize": "400% 400%",
    "backgroundPosition": "0% 0%"
  },
  "jinlingzi": {
    "src": "/assets/preview/sprites/generated/produce-preview-08.png",
    "columns": 4,
    "rows": 4,
    "index": 1,
    "x": 313,
    "y": 0,
    "width": 313,
    "height": 313,
    "sheetWidth": 1252,
    "sheetHeight": 1252,
    "backgroundSize": "400% 400%",
    "backgroundPosition": "33.3333% 0%"
  },
  "xianggua": {
    "src": "/assets/preview/sprites/generated/produce-preview-08.png",
    "columns": 4,
    "rows": 4,
    "index": 2,
    "x": 626,
    "y": 0,
    "width": 313,
    "height": 313,
    "sheetWidth": 1252,
    "sheetHeight": 1252,
    "backgroundSize": "400% 400%",
    "backgroundPosition": "66.6667% 0%"
  },
  "fo-shougan": {
    "src": "/assets/preview/sprites/generated/produce-preview-08.png",
    "columns": 4,
    "rows": 4,
    "index": 3,
    "x": 939,
    "y": 0,
    "width": 313,
    "height": 313,
    "sheetWidth": 1252,
    "sheetHeight": 1252,
    "backgroundSize": "400% 400%",
    "backgroundPosition": "100% 0%"
  },
  "qingjinju": {
    "src": "/assets/preview/sprites/generated/produce-preview-08.png",
    "columns": 4,
    "rows": 4,
    "index": 4,
    "x": 0,
    "y": 313,
    "width": 313,
    "height": 313,
    "sheetWidth": 1252,
    "sheetHeight": 1252,
    "backgroundSize": "400% 400%",
    "backgroundPosition": "0% 33.3333%"
  },
  "wogan": {
    "src": "/assets/preview/sprites/generated/produce-preview-08.png",
    "columns": 4,
    "rows": 4,
    "index": 5,
    "x": 313,
    "y": 313,
    "width": 313,
    "height": 313,
    "sheetWidth": 1252,
    "sheetHeight": 1252,
    "backgroundSize": "400% 400%",
    "backgroundPosition": "33.3333% 33.3333%"
  },
  "chunjian": {
    "src": "/assets/preview/sprites/generated/produce-preview-08.png",
    "columns": 4,
    "rows": 4,
    "index": 6,
    "x": 626,
    "y": 313,
    "width": 313,
    "height": 313,
    "sheetWidth": 1252,
    "sheetHeight": 1252,
    "backgroundSize": "400% 400%",
    "backgroundPosition": "66.6667% 33.3333%"
  },
  "qiyiguo": {
    "src": "/assets/preview/sprites/generated/produce-preview-08.png",
    "columns": 4,
    "rows": 4,
    "index": 7,
    "x": 939,
    "y": 313,
    "width": 313,
    "height": 313,
    "sheetWidth": 1252,
    "sheetHeight": 1252,
    "backgroundSize": "400% 400%",
    "backgroundPosition": "100% 33.3333%"
  },
  "xuelianguo": {
    "src": "/assets/preview/sprites/generated/produce-preview-08.png",
    "columns": 4,
    "rows": 4,
    "index": 8,
    "x": 0,
    "y": 626,
    "width": 313,
    "height": 313,
    "sheetWidth": 1252,
    "sheetHeight": 1252,
    "backgroundSize": "400% 400%",
    "backgroundPosition": "0% 66.6667%"
  },
  "jielan": {
    "src": "/assets/preview/sprites/generated/produce-preview-08.png",
    "columns": 4,
    "rows": 4,
    "index": 9,
    "x": 313,
    "y": 626,
    "width": 313,
    "height": 313,
    "sheetWidth": 1252,
    "sheetHeight": 1252,
    "backgroundSize": "400% 400%",
    "backgroundPosition": "33.3333% 66.6667%"
  },
  "caixin": {
    "src": "/assets/preview/sprites/generated/produce-preview-08.png",
    "columns": 4,
    "rows": 4,
    "index": 10,
    "x": 626,
    "y": 626,
    "width": 313,
    "height": 313,
    "sheetWidth": 1252,
    "sheetHeight": 1252,
    "backgroundSize": "400% 400%",
    "backgroundPosition": "66.6667% 66.6667%"
  },
  "tonghao": {
    "src": "/assets/preview/sprites/generated/produce-preview-08.png",
    "columns": 4,
    "rows": 4,
    "index": 11,
    "x": 939,
    "y": 626,
    "width": 313,
    "height": 313,
    "sheetWidth": 1252,
    "sheetHeight": 1252,
    "backgroundSize": "400% 400%",
    "backgroundPosition": "100% 66.6667%"
  },
  "wawacai": {
    "src": "/assets/preview/sprites/generated/produce-preview-08.png",
    "columns": 4,
    "rows": 4,
    "index": 12,
    "x": 0,
    "y": 939,
    "width": 313,
    "height": 313,
    "sheetWidth": 1252,
    "sheetHeight": 1252,
    "backgroundSize": "400% 400%",
    "backgroundPosition": "0% 100%"
  },
  "zijinglan": {
    "src": "/assets/preview/sprites/generated/produce-preview-08.png",
    "columns": 4,
    "rows": 4,
    "index": 13,
    "x": 313,
    "y": 939,
    "width": 313,
    "height": 313,
    "sheetWidth": 1252,
    "sheetHeight": 1252,
    "backgroundSize": "400% 400%",
    "backgroundPosition": "33.3333% 100%"
  },
  "yuyiglan": {
    "src": "/assets/preview/sprites/generated/produce-preview-08.png",
    "columns": 4,
    "rows": 4,
    "index": 14,
    "x": 626,
    "y": 939,
    "width": 313,
    "height": 313,
    "sheetWidth": 1252,
    "sheetHeight": 1252,
    "backgroundSize": "400% 400%",
    "backgroundPosition": "66.6667% 100%"
  },
  "baozi-ganlan": {
    "src": "/assets/preview/sprites/generated/produce-preview-08.png",
    "columns": 4,
    "rows": 4,
    "index": 15,
    "x": 939,
    "y": 939,
    "width": 313,
    "height": 313,
    "sheetWidth": 1252,
    "sheetHeight": 1252,
    "backgroundSize": "400% 400%",
    "backgroundPosition": "100% 100%"
  },
  "pilan": {
    "src": "/assets/preview/sprites/generated/produce-preview-09.png",
    "columns": 4,
    "rows": 4,
    "index": 0,
    "x": 0,
    "y": 0,
    "width": 313,
    "height": 313,
    "sheetWidth": 1252,
    "sheetHeight": 1252,
    "backgroundSize": "400% 400%",
    "backgroundPosition": "0% 0%"
  },
  "jie-cai": {
    "src": "/assets/preview/sprites/generated/produce-preview-09.png",
    "columns": 4,
    "rows": 4,
    "index": 1,
    "x": 313,
    "y": 0,
    "width": 313,
    "height": 313,
    "sheetWidth": 1252,
    "sheetHeight": 1252,
    "backgroundSize": "400% 400%",
    "backgroundPosition": "33.3333% 0%"
  },
  "muer-cai": {
    "src": "/assets/preview/sprites/generated/produce-preview-09.png",
    "columns": 4,
    "rows": 4,
    "index": 2,
    "x": 626,
    "y": 0,
    "width": 313,
    "height": 313,
    "sheetWidth": 1252,
    "sheetHeight": 1252,
    "backgroundSize": "400% 400%",
    "backgroundPosition": "66.6667% 0%"
  },
  "zhimasai": {
    "src": "/assets/preview/sprites/generated/produce-preview-09.png",
    "columns": 4,
    "rows": 4,
    "index": 3,
    "x": 939,
    "y": 0,
    "width": 313,
    "height": 313,
    "sheetWidth": 1252,
    "sheetHeight": 1252,
    "backgroundSize": "400% 400%",
    "backgroundPosition": "100% 0%"
  },
  "luomashengcai": {
    "src": "/assets/preview/sprites/generated/produce-preview-09.png",
    "columns": 4,
    "rows": 4,
    "index": 4,
    "x": 0,
    "y": 313,
    "width": 313,
    "height": 313,
    "sheetWidth": 1252,
    "sheetHeight": 1252,
    "backgroundSize": "400% 400%",
    "backgroundPosition": "0% 33.3333%"
  },
  "luokui": {
    "src": "/assets/preview/sprites/generated/produce-preview-09.png",
    "columns": 4,
    "rows": 4,
    "index": 5,
    "x": 313,
    "y": 313,
    "width": 313,
    "height": 313,
    "sheetWidth": 1252,
    "sheetHeight": 1252,
    "backgroundSize": "400% 400%",
    "backgroundPosition": "33.3333% 33.3333%"
  },
  "hongxiancai": {
    "src": "/assets/preview/sprites/generated/produce-preview-09.png",
    "columns": 4,
    "rows": 4,
    "index": 6,
    "x": 626,
    "y": 313,
    "width": 313,
    "height": 313,
    "sheetWidth": 1252,
    "sheetHeight": 1252,
    "backgroundSize": "400% 400%",
    "backgroundPosition": "66.6667% 33.3333%"
  },
  "naitangcai": {
    "src": "/assets/preview/sprites/generated/produce-preview-09.png",
    "columns": 4,
    "rows": 4,
    "index": 7,
    "x": 939,
    "y": 313,
    "width": 313,
    "height": 313,
    "sheetWidth": 1252,
    "sheetHeight": 1252,
    "backgroundSize": "400% 400%",
    "backgroundPosition": "100% 33.3333%"
  },
  "wosun": {
    "src": "/assets/preview/sprites/generated/produce-preview-09.png",
    "columns": 4,
    "rows": 4,
    "index": 8,
    "x": 0,
    "y": 626,
    "width": 313,
    "height": 313,
    "sheetWidth": 1252,
    "sheetHeight": 1252,
    "backgroundSize": "400% 400%",
    "backgroundPosition": "0% 66.6667%"
  },
  "suanmiao": {
    "src": "/assets/preview/sprites/generated/produce-preview-09.png",
    "columns": 4,
    "rows": 4,
    "index": 9,
    "x": 313,
    "y": 626,
    "width": 313,
    "height": 313,
    "sheetWidth": 1252,
    "sheetHeight": 1252,
    "backgroundSize": "400% 400%",
    "backgroundPosition": "33.3333% 66.6667%"
  },
  "jiuhuang": {
    "src": "/assets/preview/sprites/generated/produce-preview-09.png",
    "columns": 4,
    "rows": 4,
    "index": 10,
    "x": 626,
    "y": 626,
    "width": 313,
    "height": 313,
    "sheetWidth": 1252,
    "sheetHeight": 1252,
    "backgroundSize": "400% 400%",
    "backgroundPosition": "66.6667% 66.6667%"
  },
  "hudou": {
    "src": "/assets/preview/sprites/generated/produce-preview-09.png",
    "columns": 4,
    "rows": 4,
    "index": 11,
    "x": 939,
    "y": 626,
    "width": 313,
    "height": 313,
    "sheetWidth": 1252,
    "sheetHeight": 1252,
    "backgroundSize": "400% 400%",
    "backgroundPosition": "100% 66.6667%"
  },
  "biandou": {
    "src": "/assets/preview/sprites/generated/produce-preview-09.png",
    "columns": 4,
    "rows": 4,
    "index": 12,
    "x": 0,
    "y": 939,
    "width": 313,
    "height": 313,
    "sheetWidth": 1252,
    "sheetHeight": 1252,
    "backgroundSize": "400% 400%",
    "backgroundPosition": "0% 100%"
  },
  "helandou": {
    "src": "/assets/preview/sprites/generated/produce-preview-09.png",
    "columns": 4,
    "rows": 4,
    "index": 13,
    "x": 313,
    "y": 939,
    "width": 313,
    "height": 313,
    "sheetWidth": 1252,
    "sheetHeight": 1252,
    "backgroundSize": "400% 400%",
    "backgroundPosition": "33.3333% 100%"
  },
  "wandoumiao": {
    "src": "/assets/preview/sprites/generated/produce-preview-09.png",
    "columns": 4,
    "rows": 4,
    "index": 14,
    "x": 626,
    "y": 939,
    "width": 313,
    "height": 313,
    "sheetWidth": 1252,
    "sheetHeight": 1252,
    "backgroundSize": "400% 400%",
    "backgroundPosition": "66.6667% 100%"
  },
  "daodou": {
    "src": "/assets/preview/sprites/generated/produce-preview-09.png",
    "columns": 4,
    "rows": 4,
    "index": 15,
    "x": 939,
    "y": 939,
    "width": 313,
    "height": 313,
    "sheetWidth": 1252,
    "sheetHeight": 1252,
    "backgroundSize": "400% 400%",
    "backgroundPosition": "100% 100%"
  },
  "chayote-miao": {
    "src": "/assets/preview/sprites/generated/produce-preview-10.png",
    "columns": 4,
    "rows": 4,
    "index": 0,
    "x": 0,
    "y": 0,
    "width": 313,
    "height": 313,
    "sheetWidth": 1252,
    "sheetHeight": 1252,
    "backgroundSize": "400% 400%",
    "backgroundPosition": "0% 0%"
  },
  "baizhuo": {
    "src": "/assets/preview/sprites/generated/produce-preview-10.png",
    "columns": 4,
    "rows": 4,
    "index": 1,
    "x": 313,
    "y": 0,
    "width": 313,
    "height": 313,
    "sheetWidth": 1252,
    "sheetHeight": 1252,
    "backgroundSize": "400% 400%",
    "backgroundPosition": "33.3333% 0%"
  },
  "yutou": {
    "src": "/assets/preview/sprites/generated/produce-preview-10.png",
    "columns": 4,
    "rows": 4,
    "index": 2,
    "x": 626,
    "y": 0,
    "width": 313,
    "height": 313,
    "sheetWidth": 1252,
    "sheetHeight": 1252,
    "backgroundSize": "400% 400%",
    "backgroundPosition": "66.6667% 0%"
  },
  "moyu": {
    "src": "/assets/preview/sprites/generated/produce-preview-10.png",
    "columns": 4,
    "rows": 4,
    "index": 3,
    "x": 939,
    "y": 0,
    "width": 313,
    "height": 313,
    "sheetWidth": 1252,
    "sheetHeight": 1252,
    "backgroundSize": "400% 400%",
    "backgroundPosition": "100% 0%"
  },
  "cigu": {
    "src": "/assets/preview/sprites/generated/produce-preview-10.png",
    "columns": 4,
    "rows": 4,
    "index": 4,
    "x": 0,
    "y": 313,
    "width": 313,
    "height": 313,
    "sheetWidth": 1252,
    "sheetHeight": 1252,
    "backgroundSize": "400% 400%",
    "backgroundPosition": "0% 33.3333%"
  },
  "shuiqincai": {
    "src": "/assets/preview/sprites/generated/produce-preview-10.png",
    "columns": 4,
    "rows": 4,
    "index": 5,
    "x": 313,
    "y": 313,
    "width": 313,
    "height": 313,
    "sheetWidth": 1252,
    "sheetHeight": 1252,
    "backgroundSize": "400% 400%",
    "backgroundPosition": "33.3333% 33.3333%"
  },
  "chuncai": {
    "src": "/assets/preview/sprites/generated/produce-preview-10.png",
    "columns": 4,
    "rows": 4,
    "index": 6,
    "x": 626,
    "y": 313,
    "width": 313,
    "height": 313,
    "sheetWidth": 1252,
    "sheetHeight": 1252,
    "backgroundSize": "400% 400%",
    "backgroundPosition": "66.6667% 33.3333%"
  },
  "haidai": {
    "src": "/assets/preview/sprites/generated/produce-preview-10.png",
    "columns": 4,
    "rows": 4,
    "index": 7,
    "x": 939,
    "y": 313,
    "width": 313,
    "height": 313,
    "sheetWidth": 1252,
    "sheetHeight": 1252,
    "backgroundSize": "400% 400%",
    "backgroundPosition": "100% 33.3333%"
  },
  "zicai": {
    "src": "/assets/preview/sprites/generated/produce-preview-10.png",
    "columns": 4,
    "rows": 4,
    "index": 8,
    "x": 0,
    "y": 626,
    "width": 313,
    "height": 313,
    "sheetWidth": 1252,
    "sheetHeight": 1252,
    "backgroundSize": "400% 400%",
    "backgroundPosition": "0% 66.6667%"
  },
  "jiucaihua": {
    "src": "/assets/preview/sprites/generated/produce-preview-10.png",
    "columns": 4,
    "rows": 4,
    "index": 9,
    "x": 313,
    "y": 626,
    "width": 313,
    "height": 313,
    "sheetWidth": 1252,
    "sheetHeight": 1252,
    "backgroundSize": "400% 400%",
    "backgroundPosition": "33.3333% 66.6667%"
  },
  "nanhuateng": {
    "src": "/assets/preview/sprites/generated/produce-preview-10.png",
    "columns": 4,
    "rows": 4,
    "index": 10,
    "x": 626,
    "y": 626,
    "width": 313,
    "height": 313,
    "sheetWidth": 1252,
    "sheetHeight": 1252,
    "backgroundSize": "400% 400%",
    "backgroundPosition": "66.6667% 66.6667%"
  },
  "jizongjun": {
    "src": "/assets/preview/sprites/generated/produce-preview-10.png",
    "columns": 4,
    "rows": 4,
    "index": 11,
    "x": 939,
    "y": 626,
    "width": 313,
    "height": 313,
    "sheetWidth": 1252,
    "sheetHeight": 1252,
    "backgroundSize": "400% 400%",
    "backgroundPosition": "100% 66.6667%"
  },
  "songrong": {
    "src": "/assets/preview/sprites/generated/produce-preview-10.png",
    "columns": 4,
    "rows": 4,
    "index": 12,
    "x": 0,
    "y": 939,
    "width": 313,
    "height": 313,
    "sheetWidth": 1252,
    "sheetHeight": 1252,
    "backgroundSize": "400% 400%",
    "backgroundPosition": "0% 100%"
  },
  "muer": {
    "src": "/assets/preview/sprites/generated/produce-preview-10.png",
    "columns": 4,
    "rows": 4,
    "index": 13,
    "x": 313,
    "y": 939,
    "width": 313,
    "height": 313,
    "sheetWidth": 1252,
    "sheetHeight": 1252,
    "backgroundSize": "400% 400%",
    "backgroundPosition": "33.3333% 100%"
  },
  "zhusun": {
    "src": "/assets/preview/sprites/generated/produce-preview-10.png",
    "columns": 4,
    "rows": 4,
    "index": 14,
    "x": 626,
    "y": 939,
    "width": 313,
    "height": 313,
    "sheetWidth": 1252,
    "sheetHeight": 1252,
    "backgroundSize": "400% 400%",
    "backgroundPosition": "66.6667% 100%"
  },
  "chashugu": {
    "src": "/assets/preview/sprites/generated/produce-preview-10.png",
    "columns": 4,
    "rows": 4,
    "index": 15,
    "x": 939,
    "y": 939,
    "width": 313,
    "height": 313,
    "sheetWidth": 1252,
    "sheetHeight": 1252,
    "backgroundSize": "400% 400%",
    "backgroundPosition": "100% 100%"
  },
  "xingbaogu": {
    "src": "/assets/preview/sprites/generated/produce-preview-11.png",
    "columns": 4,
    "rows": 4,
    "index": 0,
    "x": 0,
    "y": 0,
    "width": 313,
    "height": 313,
    "sheetWidth": 1252,
    "sheetHeight": 1252,
    "backgroundSize": "400% 400%",
    "backgroundPosition": "0% 0%"
  },
  "koucai": {
    "src": "/assets/preview/sprites/generated/produce-preview-11.png",
    "columns": 4,
    "rows": 4,
    "index": 1,
    "x": 313,
    "y": 0,
    "width": 313,
    "height": 313,
    "sheetWidth": 1252,
    "sheetHeight": 1252,
    "backgroundSize": "400% 400%",
    "backgroundPosition": "33.3333% 0%"
  },
  "bawanghua": {
    "src": "/assets/preview/sprites/generated/produce-preview-11.png",
    "columns": 4,
    "rows": 4,
    "index": 2,
    "x": 626,
    "y": 0,
    "width": 313,
    "height": 313,
    "sheetWidth": 1252,
    "sheetHeight": 1252,
    "backgroundSize": "400% 400%",
    "backgroundPosition": "66.6667% 0%"
  },
  "tianqicai": {
    "src": "/assets/preview/sprites/generated/produce-preview-11.png",
    "columns": 4,
    "rows": 4,
    "index": 3,
    "x": 939,
    "y": 0,
    "width": 313,
    "height": 313,
    "sheetWidth": 1252,
    "sheetHeight": 1252,
    "backgroundSize": "400% 400%",
    "backgroundPosition": "100% 0%"
  },
  "huoxiang": {
    "src": "/assets/preview/sprites/generated/produce-preview-11.png",
    "columns": 4,
    "rows": 4,
    "index": 4,
    "x": 0,
    "y": 313,
    "width": 313,
    "height": 313,
    "sheetWidth": 1252,
    "sheetHeight": 1252,
    "backgroundSize": "400% 400%",
    "backgroundPosition": "0% 33.3333%"
  },
  "zijisu": {
    "src": "/assets/preview/sprites/generated/produce-preview-11.png",
    "columns": 4,
    "rows": 4,
    "index": 5,
    "x": 313,
    "y": 313,
    "width": 313,
    "height": 313,
    "sheetWidth": 1252,
    "sheetHeight": 1252,
    "backgroundSize": "400% 400%",
    "backgroundPosition": "33.3333% 33.3333%"
  },
  "luole": {
    "src": "/assets/preview/sprites/generated/produce-preview-11.png",
    "columns": 4,
    "rows": 4,
    "index": 6,
    "x": 626,
    "y": 313,
    "width": 313,
    "height": 313,
    "sheetWidth": 1252,
    "sheetHeight": 1252,
    "backgroundSize": "400% 400%",
    "backgroundPosition": "66.6667% 33.3333%"
  },
  "baimicai": {
    "src": "/assets/preview/sprites/generated/produce-preview-11.png",
    "columns": 4,
    "rows": 4,
    "index": 7,
    "x": 939,
    "y": 313,
    "width": 313,
    "height": 313,
    "sheetWidth": 1252,
    "sheetHeight": 1252,
    "backgroundSize": "400% 400%",
    "backgroundPosition": "100% 33.3333%"
  }
}
